demo_ezto/__init__.py
demo_ezto/create_project.py
demo_ezto/main.py
demo_ezto-0.1.0.dist-info/METADATA
demo_ezto-0.1.0.dist-info/WHEEL
demo_ezto-0.1.0.dist-info/entry_points.txt
demo_ezto-0.1.0.dist-info/top_level.txt
demo_ezto-0.1.0.dist-info/RECORD
